{
  "annotations": {
    "list": [
      {
        "builtIn": 1,
        "datasource": { "type": "grafana", "uid": "-- Grafana --" },
        "enable": true,
        "hide": true,
        "iconColor": "rgba(0, 211, 255, 1)",
        "name": "Annotations & Alerts",
        "type": "dashboard"
      }
    ]
  },
  "description": "Nexus Repository Manager metrics — JVM, HTTP, storage, connections",
  "editable": true,
  "fiscalYearStartMonth": 0,
  "graphTooltip": 1,
  "id": null,
  "links": [],
  "panels": [
    {
      "collapsed": false,
      "gridPos": { "h": 1, "w": 24, "x": 0, "y": 0 },
      "id": 100,
      "title": "JVM Memory",
      "type": "row"
    },
    {
      "datasource": { "type": "prometheus", "uid": "${datasource}" },
      "fieldConfig": {
        "defaults": {
          "color": { "mode": "palette-classic" },
          "custom": {
            "axisBorderShow": false,
            "axisLabel": "",
            "fillOpacity": 20,
            "lineWidth": 2,
            "scaleDistribution": { "type": "linear" },
            "showPoints": "never",
            "spanNulls": false
          },
          "unit": "bytes"
        },
        "overrides": []
      },
      "gridPos": { "h": 8, "w": 12, "x": 0, "y": 1 },
      "id": 1,
      "options": {
        "legend": { "calcs": ["lastNotNull", "max"], "displayMode": "table", "placement": "bottom" },
        "tooltip": { "mode": "multi", "sort": "desc" }
      },
      "title": "JVM Heap Memory",
      "type": "timeseries",
      "targets": [
        {
          "datasource": { "type": "prometheus", "uid": "${datasource}" },
          "expr": "jvm_memory_bytes_used{namespace=\"nexus\", area=\"heap\"}",
          "legendFormat": "Used — {{id}}",
          "refId": "A"
        },
        {
          "datasource": { "type": "prometheus", "uid": "${datasource}" },
          "expr": "jvm_memory_bytes_committed{namespace=\"nexus\", area=\"heap\"}",
          "legendFormat": "Committed — {{id}}",
          "refId": "B"
        },
        {
          "datasource": { "type": "prometheus", "uid": "${datasource}" },
          "expr": "jvm_memory_bytes_max{namespace=\"nexus\", area=\"heap\"}",
          "legendFormat": "Max — {{id}}",
          "refId": "C"
        }
      ]
    },
    {
      "datasource": { "type": "prometheus", "uid": "${datasource}" },
      "fieldConfig": {
        "defaults": {
          "color": { "mode": "palette-classic" },
          "custom": {
            "axisBorderShow": false,
            "axisLabel": "",
            "fillOpacity": 20,
            "lineWidth": 2,
            "scaleDistribution": { "type": "linear" },
            "showPoints": "never",
            "spanNulls": false
          },
          "unit": "bytes"
        },
        "overrides": []
      },
      "gridPos": { "h": 8, "w": 12, "x": 12, "y": 1 },
      "id": 2,
      "options": {
        "legend": { "calcs": ["lastNotNull", "max"], "displayMode": "table", "placement": "bottom" },
        "tooltip": { "mode": "multi", "sort": "desc" }
      },
      "title": "JVM Non-Heap Memory",
      "type": "timeseries",
      "targets": [
        {
          "datasource": { "type": "prometheus", "uid": "${datasource}" },
          "expr": "jvm_memory_bytes_used{namespace=\"nexus\", area=\"nonheap\"}",
          "legendFormat": "Used — {{id}}",
          "refId": "A"
        },
        {
          "datasource": { "type": "prometheus", "uid": "${datasource}" },
          "expr": "jvm_memory_bytes_committed{namespace=\"nexus\", area=\"nonheap\"}",
          "legendFormat": "Committed — {{id}}",
          "refId": "B"
        }
      ]
    },
    {
      "collapsed": false,
      "gridPos": { "h": 1, "w": 24, "x": 0, "y": 9 },
      "id": 101,
      "title": "HTTP Requests",
      "type": "row"
    },
    {
      "datasource": { "type": "prometheus", "uid": "${datasource}" },
      "fieldConfig": {
        "defaults": {
          "color": { "mode": "palette-classic" },
          "custom": {
            "axisBorderShow": false,
            "axisLabel": "req/s",
            "fillOpacity": 10,
            "lineWidth": 2,
            "scaleDistribution": { "type": "linear" },
            "showPoints": "never",
            "spanNulls": false
          },
          "unit": "reqps"
        },
        "overrides": []
      },
      "gridPos": { "h": 8, "w": 12, "x": 0, "y": 10 },
      "id": 3,
      "options": {
        "legend": { "calcs": ["mean", "max"], "displayMode": "table", "placement": "bottom" },
        "tooltip": { "mode": "multi", "sort": "desc" }
      },
      "title": "HTTP Request Rate by Method",
      "type": "timeseries",
      "targets": [
        {
          "datasource": { "type": "prometheus", "uid": "${datasource}" },
          "expr": "sum by (method) (rate(http_server_requests_seconds_count{namespace=\"nexus\"}[5m]))",
          "legendFormat": "{{method}}",
          "refId": "A"
        }
      ]
    },
    {
      "datasource": { "type": "prometheus", "uid": "${datasource}" },
      "fieldConfig": {
        "defaults": {
          "color": { "mode": "palette-classic" },
          "custom": {
            "axisBorderShow": false,
            "axisLabel": "",
            "fillOpacity": 10,
            "lineWidth": 2,
            "scaleDistribution": { "type": "linear" },
            "showPoints": "never",
            "spanNulls": false
          },
          "unit": "s"
        },
        "overrides": []
      },
      "gridPos": { "h": 8, "w": 12, "x": 12, "y": 10 },
      "id": 4,
      "options": {
        "legend": { "calcs": ["mean", "max"], "displayMode": "table", "placement": "bottom" },
        "tooltip": { "mode": "multi", "sort": "desc" }
      },
      "title": "HTTP Request Duration (p95)",
      "type": "timeseries",
      "targets": [
        {
          "datasource": { "type": "prometheus", "uid": "${datasource}" },
          "expr": "histogram_quantile(0.95, sum by (le, method) (rate(http_server_requests_seconds_bucket{namespace=\"nexus\"}[5m])))",
          "legendFormat": "p95 {{method}}",
          "refId": "A"
        },
        {
          "datasource": { "type": "prometheus", "uid": "${datasource}" },
          "expr": "histogram_quantile(0.50, sum by (le, method) (rate(http_server_requests_seconds_bucket{namespace=\"nexus\"}[5m])))",
          "legendFormat": "p50 {{method}}",
          "refId": "B"
        }
      ]
    },
    {
      "collapsed": false,
      "gridPos": { "h": 1, "w": 24, "x": 0, "y": 18 },
      "id": 102,
      "title": "Connections & Threads",
      "type": "row"
    },
    {
      "datasource": { "type": "prometheus", "uid": "${datasource}" },
      "fieldConfig": {
        "defaults": {
          "color": { "mode": "palette-classic" },
          "custom": {
            "axisBorderShow": false,
            "axisLabel": "",
            "fillOpacity": 20,
            "lineWidth": 2,
            "scaleDistribution": { "type": "linear" },
            "showPoints": "never",
            "spanNulls": false
          },
          "unit": "short"
        },
        "overrides": []
      },
      "gridPos": { "h": 8, "w": 12, "x": 0, "y": 19 },
      "id": 5,
      "options": {
        "legend": { "calcs": ["lastNotNull"], "displayMode": "table", "placement": "bottom" },
        "tooltip": { "mode": "multi", "sort": "desc" }
      },
      "title": "Active Connections",
      "type": "timeseries",
      "targets": [
        {
          "datasource": { "type": "prometheus", "uid": "${datasource}" },
          "expr": "jetty_connections_current{namespace=\"nexus\"}",
          "legendFormat": "Current",
          "refId": "A"
        },
        {
          "datasource": { "type": "prometheus", "uid": "${datasource}" },
          "expr": "jetty_connections_max{namespace=\"nexus\"}",
          "legendFormat": "Max",
          "refId": "B"
        }
      ]
    },
    {
      "datasource": { "type": "prometheus", "uid": "${datasource}" },
      "fieldConfig": {
        "defaults": {
          "color": { "mode": "palette-classic" },
          "custom": {
            "axisBorderShow": false,
            "axisLabel": "",
            "fillOpacity": 20,
            "lineWidth": 2,
            "scaleDistribution": { "type": "linear" },
            "showPoints": "never",
            "spanNulls": false
          },
          "unit": "short"
        },
        "overrides": []
      },
      "gridPos": { "h": 8, "w": 12, "x": 12, "y": 19 },
      "id": 6,
      "options": {
        "legend": { "calcs": ["lastNotNull"], "displayMode": "table", "placement": "bottom" },
        "tooltip": { "mode": "multi", "sort": "desc" }
      },
      "title": "JVM Threads",
      "type": "timeseries",
      "targets": [
        {
          "datasource": { "type": "prometheus", "uid": "${datasource}" },
          "expr": "jvm_threads_current{namespace=\"nexus\"}",
          "legendFormat": "Current",
          "refId": "A"
        },
        {
          "datasource": { "type": "prometheus", "uid": "${datasource}" },
          "expr": "jvm_threads_daemon{namespace=\"nexus\"}",
          "legendFormat": "Daemon",
          "refId": "B"
        },
        {
          "datasource": { "type": "prometheus", "uid": "${datasource}" },
          "expr": "jvm_threads_peak{namespace=\"nexus\"}",
          "legendFormat": "Peak",
          "refId": "C"
        }
      ]
    },
    {
      "collapsed": false,
      "gridPos": { "h": 1, "w": 24, "x": 0, "y": 27 },
      "id": 103,
      "title": "JVM GC & Uptime",
      "type": "row"
    },
    {
      "datasource": { "type": "prometheus", "uid": "${datasource}" },
      "fieldConfig": {
        "defaults": {
          "color": { "mode": "palette-classic" },
          "custom": {
            "axisBorderShow": false,
            "axisLabel": "",
            "fillOpacity": 20,
            "lineWidth": 2,
            "scaleDistribution": { "type": "linear" },
            "showPoints": "never",
            "spanNulls": false
          },
          "unit": "s"
        },
        "overrides": []
      },
      "gridPos": { "h": 8, "w": 12, "x": 0, "y": 28 },
      "id": 7,
      "options": {
        "legend": { "calcs": ["mean", "max"], "displayMode": "table", "placement": "bottom" },
        "tooltip": { "mode": "multi", "sort": "desc" }
      },
      "title": "GC Pause Duration Rate",
      "type": "timeseries",
      "targets": [
        {
          "datasource": { "type": "prometheus", "uid": "${datasource}" },
          "expr": "rate(jvm_gc_collection_seconds_sum{namespace=\"nexus\"}[5m])",
          "legendFormat": "{{gc}}",
          "refId": "A"
        }
      ]
    },
    {
      "datasource": { "type": "prometheus", "uid": "${datasource}" },
      "fieldConfig": {
        "defaults": {
          "color": { "mode": "thresholds" },
          "thresholds": {
            "mode": "absolute",
            "steps": [
              { "color": "red", "value": null },
              { "color": "green", "value": 3600 }
            ]
          },
          "unit": "s"
        },
        "overrides": []
      },
      "gridPos": { "h": 8, "w": 6, "x": 12, "y": 28 },
      "id": 8,
      "options": {
        "colorMode": "background",
        "graphMode": "none",
        "justifyMode": "auto",
        "orientation": "auto",
        "reduceOptions": { "calcs": ["lastNotNull"], "fields": "", "values": false },
        "textMode": "auto"
      },
      "title": "Uptime",
      "type": "stat",
      "targets": [
        {
          "datasource": { "type": "prometheus", "uid": "${datasource}" },
          "expr": "process_uptime_seconds{namespace=\"nexus\"}",
          "legendFormat": "Uptime",
          "refId": "A"
        }
      ]
    },
    {
      "datasource": { "type": "prometheus", "uid": "${datasource}" },
      "fieldConfig": {
        "defaults": {
          "color": { "mode": "thresholds" },
          "thresholds": {
            "mode": "absolute",
            "steps": [
              { "color": "green", "value": null },
              { "color": "yellow", "value": 0.7 },
              { "color": "red", "value": 0.9 }
            ]
          },
          "unit": "percentunit",
          "min": 0,
          "max": 1
        },
        "overrides": []
      },
      "gridPos": { "h": 8, "w": 6, "x": 18, "y": 28 },
      "id": 9,
      "options": {
        "colorMode": "background",
        "graphMode": "area",
        "justifyMode": "auto",
        "orientation": "auto",
        "reduceOptions": { "calcs": ["lastNotNull"], "fields": "", "values": false },
        "textMode": "auto"
      },
      "title": "Heap Usage %",
      "type": "stat",
      "targets": [
        {
          "datasource": { "type": "prometheus", "uid": "${datasource}" },
          "expr": "sum(jvm_memory_bytes_used{namespace=\"nexus\", area=\"heap\"}) / sum(jvm_memory_bytes_max{namespace=\"nexus\", area=\"heap\"})",
          "legendFormat": "Heap %",
          "refId": "A"
        }
      ]
    },
    {
      "collapsed": false,
      "gridPos": { "h": 1, "w": 24, "x": 0, "y": 36 },
      "id": 104,
      "title": "Storage",
      "type": "row"
    },
    {
      "datasource": { "type": "prometheus", "uid": "${datasource}" },
      "fieldConfig": {
        "defaults": {
          "color": { "mode": "palette-classic" },
          "custom": {
            "axisBorderShow": false,
            "axisLabel": "",
            "fillOpacity": 20,
            "lineWidth": 2,
            "scaleDistribution": { "type": "linear" },
            "showPoints": "never",
            "spanNulls": false
          },
          "unit": "bytes"
        },
        "overrides": []
      },
      "gridPos": { "h": 8, "w": 12, "x": 0, "y": 37 },
      "id": 10,
      "options": {
        "legend": { "calcs": ["lastNotNull"], "displayMode": "table", "placement": "bottom" },
        "tooltip": { "mode": "multi", "sort": "desc" }
      },
      "title": "Blob Store Size",
      "type": "timeseries",
      "targets": [
        {
          "datasource": { "type": "prometheus", "uid": "${datasource}" },
          "expr": "nxrm_blob_store_total_size_bytes{namespace=\"nexus\"}",
          "legendFormat": "{{blob_store_name}}",
          "refId": "A"
        }
      ]
    },
    {
      "datasource": { "type": "prometheus", "uid": "${datasource}" },
      "fieldConfig": {
        "defaults": {
          "color": { "mode": "palette-classic" },
          "custom": {
            "axisBorderShow": false,
            "axisLabel": "",
            "fillOpacity": 10,
            "lineWidth": 2,
            "scaleDistribution": { "type": "linear" },
            "showPoints": "never",
            "spanNulls": false
          },
          "unit": "short"
        },
        "overrides": []
      },
      "gridPos": { "h": 8, "w": 12, "x": 12, "y": 37 },
      "id": 11,
      "options": {
        "legend": { "calcs": ["lastNotNull"], "displayMode": "table", "placement": "bottom" },
        "tooltip": { "mode": "multi", "sort": "desc" }
      },
      "title": "Blob Store Blob Count",
      "type": "timeseries",
      "targets": [
        {
          "datasource": { "type": "prometheus", "uid": "${datasource}" },
          "expr": "nxrm_blob_store_blob_count{namespace=\"nexus\"}",
          "legendFormat": "{{blob_store_name}}",
          "refId": "A"
        }
      ]
    }
  ],
  "schemaVersion": 39,
  "tags": ["nexus", "homelab"],
  "templating": {
    "list": [
      {
        "current": { "selected": false, "text": "Prometheus", "value": "prometheus" },
        "hide": 0,
        "includeAll": false,
        "label": "Datasource",
        "multi": false,
        "name": "datasource",
        "options": [],
        "query": "prometheus",
        "refresh": 1,
        "type": "datasource"
      }
    ]
  },
  "time": { "from": "now-6h", "to": "now" },
  "timepicker": {},
  "timezone": "",
  "title": "Nexus Repository Manager",
  "uid": "nexus-repository",
  "version": 1
}
